your_package/__init__.py
ovs_system-1.1.0.dist-info/LICENSE
ovs_system-1.1.0.dist-info/METADATA
ovs_system-1.1.0.dist-info/WHEEL
ovs_system-1.1.0.dist-info/top_level.txt
ovs_system-1.1.0.dist-info/RECORD
