Metadata-Version: 2.1
Name: ovs-system
Version: 1.1.0
Summary: Online Variables System: Manage variables with Firebase
Home-page: https://github.com/e500ky/ovs-system
Author: ArsTech
Author-email: arstechai@gmail.com
Classifier: Programming Language :: Python :: 3
Classifier: License :: OSI Approved :: MIT License
Classifier: Operating System :: OS Independent
Requires-Python: >=3.6
License-File: LICENSE
Requires-Dist: firebase-admin>=6.0.0
Requires-Dist: python-dotenv>=1.0.0
